textwiz/__init__.py
textwiz/cli.py
textwiz/loader.py
textwiz/configs/__init__.py
textwiz/configs/causal/__init__.py
textwiz/configs/causal/bloom.py
textwiz/configs/causal/code_llama.py
textwiz/configs/causal/codegen.py
textwiz/configs/causal/codegen2.py
textwiz/configs/causal/command.py
textwiz/configs/causal/dialo_gpt.py
textwiz/configs/causal/gpt2.py
textwiz/configs/causal/gpt_j_neo.py
textwiz/configs/causal/llama2.py
textwiz/configs/causal/llama3.py
textwiz/configs/causal/llama31.py
textwiz/configs/causal/mistral.py
textwiz/configs/causal/opt.py
textwiz/configs/causal/stable_lm.py
textwiz/configs/causal/star_chat.py
textwiz/configs/causal/star_coder.py
textwiz/configs/causal/starling.py
textwiz/configs/causal/vicuna.py
textwiz/configs/causal/zephyr.py
textwiz/configs/embedding/__init__.py
textwiz/configs/embedding/mistral.py
textwiz/data/memory_estimator/new/infos.json
textwiz/data/memory_estimator/new/causal/code-llama-13B/bfloat16.json
textwiz/data/memory_estimator/new/causal/code-llama-13B-instruct/bfloat16.json
textwiz/data/memory_estimator/new/causal/code-llama-13B-python/bfloat16.json
textwiz/data/memory_estimator/new/causal/code-llama-34B/bfloat16.json
textwiz/data/memory_estimator/new/causal/code-llama-34B-instruct/bfloat16.json
textwiz/data/memory_estimator/new/causal/code-llama-34B-python/bfloat16.json
textwiz/data/memory_estimator/new/causal/code-llama-70B/bfloat16.json
textwiz/data/memory_estimator/new/causal/code-llama-70B-instruct/bfloat16.json
textwiz/data/memory_estimator/new/causal/code-llama-70B-python/bfloat16.json
textwiz/data/memory_estimator/new/causal/code-llama-7B/bfloat16.json
textwiz/data/memory_estimator/new/causal/code-llama-7B-instruct/bfloat16.json
textwiz/data/memory_estimator/new/causal/code-llama-7B-python/bfloat16.json
textwiz/data/memory_estimator/new/causal/codegen-16B/float16.json
textwiz/data/memory_estimator/new/causal/codegen-2B/float16.json
textwiz/data/memory_estimator/new/causal/codegen-350M/float16.json
textwiz-0.7.1.dist-info/LICENSE
textwiz-0.7.1.dist-info/METADATA
textwiz-0.7.1.dist-info/WHEEL
textwiz-0.7.1.dist-info/entry_points.txt
textwiz-0.7.1.dist-info/top_level.txt
textwiz-0.7.1.dist-info/RECORD
