Metadata-Version: 2.1
Name: textwiz
Version: 0.7.1
Summary: An even simpler way to use open-source LLMs.
Author-email: Cyril Vallez <cyril.vallez@gmail.com>
Maintainer-email: Cyril Vallez <cyril.vallez@gmail.com>
License: Apache License
Project-URL: Homepage, https://github.com/Cyrilvallez/TextWiz
Project-URL: Issues, https://github.com/Cyrilvallez/TextWiz/issues
Project-URL: Changelog, https://github.com/Cyrilvallez/TextWiz/blob/main/CHANGELOG.md
Keywords: LLM,text-generation
Classifier: Programming Language :: Python :: 3
Classifier: License :: OSI Approved :: Apache Software License
Requires-Python: >=3.11
License-File: LICENSE
Requires-Dist: numpy
Requires-Dist: pyyaml
Requires-Dist: packaging
Requires-Dist: torch >=2.2.0
Requires-Dist: transformers >=4.42
Requires-Dist: tokenizers >=0.13.3
Requires-Dist: sentencepiece
Requires-Dist: protobuf
Requires-Dist: tiktoken
Requires-Dist: gradio
Requires-Dist: accelerate >=0.22.0
Requires-Dist: optimum >=1.12.0
Requires-Dist: bitsandbytes >=0.41.1
